automation_test_no_submodules/__init__.py
automation_test_no_submodules/api_client.py
automation_test_no_submodules/api_response.py
automation_test_no_submodules/apis/__init__.py
automation_test_no_submodules/apis/path_to_api.py
automation_test_no_submodules/apis/paths/__init__.py
automation_test_no_submodules/apis/paths/hello.py
automation_test_no_submodules/apis/tag_to_api.py
automation_test_no_submodules/apis/tags/__init__.py
automation_test_no_submodules/apis/tags/greetings_api.py
automation_test_no_submodules/apis/tags/greetings_api_generated.py
automation_test_no_submodules/apis/tags/greetings_api_raw.py
automation_test_no_submodules/client.py
automation_test_no_submodules/client.pyi
automation_test_no_submodules/client_custom.py
automation_test_no_submodules/configuration.py
automation_test_no_submodules/exceptions.py
automation_test_no_submodules/exceptions_base.py
automation_test_no_submodules/model/__init__.py
automation_test_no_submodules/model/hello_response.py
automation_test_no_submodules/model/hello_response.pyi
automation_test_no_submodules/models/__init__.py
automation_test_no_submodules/operation_parameter_map.py
automation_test_no_submodules/paths/__init__.py
automation_test_no_submodules/paths/hello/__init__.py
automation_test_no_submodules/paths/hello/get.py
automation_test_no_submodules/paths/hello/get.pyi
automation_test_no_submodules/pydantic/__init__.py
automation_test_no_submodules/pydantic/hello_response.py
automation_test_no_submodules/request_after_hook.py
automation_test_no_submodules/request_before_hook.py
automation_test_no_submodules/request_before_url_hook.py
automation_test_no_submodules/rest.py
automation_test_no_submodules/schemas.py
automation_test_no_submodules/type/__init__.py
automation_test_no_submodules/type/hello_response.py
automation_test_no_submodules/type_util.py
automation_test_no_submodules/validation_metadata.py
automation_test_no_submodules_python_sdk-1.0.6.dist-info/LICENSE
automation_test_no_submodules_python_sdk-1.0.6.dist-info/METADATA
automation_test_no_submodules_python_sdk-1.0.6.dist-info/WHEEL
automation_test_no_submodules_python_sdk-1.0.6.dist-info/RECORD
